[
  {
    "frase": "La educación es el mejor recurso para la vejez.",
    "autor": "Aristóteles"
  },
  {
    "frase": "La amistad es un alma que habita en dos cuerpos; un corazón que habita en dos almas.",
    "autor": "Aristóteles"
  },
  {
    "frase": "El hombre es por naturaleza un animal político.",
    "autor": "Aristóteles"
  },
  {
    "frase": "Somos lo que hacemos repetidamente. La excelencia, entonces, no es un acto, sino un hábito.",
    "autor": "Aristóteles"
  },
  {
    "frase": "La virtud está en el término medio.",
    "autor": "Aristóteles"
  },
  {
    "frase": "La justicia es la igualdad, para los iguales y la desigualdad para los desiguales.",
    "autor": "Aristóteles"
  },
  {
    "frase": "El hombre sabio no busca el placer, sino la ausencia de dolor.",
    "autor": "Aristóteles"
  },
  {
    "frase": "La educación es el adorno de la prosperidad y el refugio en la adversidad.",
    "autor": "Aristóteles"
  },
  {
    "frase": "La música es una ley moral. Da alma al universo, alas a la mente, vuelo a la imaginación.",
    "autor": "Platón"
  },
  {
    "frase": "La primera y mejor victoria es conquistarse a uno mismo.",
    "autor": "Platón"
  },
  {
    "frase": "El comienzo es la parte más importante del trabajo.",
    "autor": "Platón"
  },
  {
    "frase": "El amor es el deseo de la mitad que nos falta.",
    "autor": "Platón"
  },
  {
    "frase": "Podemos perdonar fácilmente a un niño que teme a la oscuridad; la verdadera tragedia es cuando los hombres temen a la luz.",
    "autor": "Platón"
  },
  {
    "frase": "El precio de desentenderse de la política es ser gobernado por los peores hombres.",
    "autor": "Platón"
  },
  {
    "frase": "El alma del hombre es inmortal e imperecedera.",
    "autor": "Platón"
  },
  {
    "frase": "El hombre es una cuerda tendida entre el animal y el superhombre.",
    "autor": "Nietzsche"
  },
  {
    "frase": "Sin música la vida sería un error.",
    "autor": "Nietzsche"
  },
  {
    "frase": "Dios ha muerto. Y nosotros lo hemos matado.",
    "autor": "Nietzsche"
  },
  {
    "frase": "Lo que no me mata, me hace más fuerte.",
    "autor": "Nietzsche"
  },
  {
    "frase": "No hay hechos, sólo interpretaciones.",
    "autor": "Nietzsche"
  },
  {
    "frase": "El hombre es algo que debe ser superado.",
    "autor": "Nietzsche"
  },
  {
    "frase": "El que tiene un porqué para vivir puede soportar casi cualquier cómo.",
    "autor": "Nietzsche"
  },
  {
    "frase": "Obra de tal modo que trates a la humanidad, tanto en tu persona como en la de cualquier otro, siempre como un fin y nunca solamente como un medio.",
    "autor": "Kant"
  },
  {
    "frase": "La felicidad no es un ideal de la razón sino de la imaginación.",
    "autor": "Kant"
  },
  {
    "frase": "El cielo estrellado sobre mí y la ley moral dentro de mí.",
    "autor": "Kant"
  },
  {
    "frase": "El hombre no es más que lo que la educación hace de él.",
    "autor": "Kant"
  },
  {
    "frase": "La libertad es la condición que hace posible la moralidad.",
    "autor": "Kant"
  },
  {
    "frase": "La experiencia sin teoría es ciega, pero la teoría sin experiencia es un mero juego intelectual.",
    "autor": "Kant"
  },
  {
    "frase": "La ilustración es la salida del hombre de su autoculpable minoría de edad.",
    "autor": "Kant"
  },
  {
    "frase": "La ciencia es conocimiento organizado. La sabiduría es la vida organizada.",
    "autor": "Kant"
  }
]
